mempool/__init__.py
mempool/api.py
mempool_api-1.0.0.dist-info/METADATA
mempool_api-1.0.0.dist-info/WHEEL
mempool_api-1.0.0.dist-info/top_level.txt
mempool_api-1.0.0.dist-info/RECORD
